voter.v
module voter (I, O);
input [3:0] I;     // I 4 men
output [3:1] O;   // O Result
reg [3:1] O;

always@ (I)
case (I)
    4'b0000:
        O=3'b001;
    4'b0001:
        O=3'b001;
    4'b0010:
        O=3'b001;
    4'b0011:
        O=3'b010;
    4'b0100:
        O=3'b001;
    4'b0101:
        O=3'b010;
    4'b0110:
        O=3'b010;
    4'b0111:
        O=3'b100;
    4'b1000:
        O=3'b001;
    4'b1001:
        O=3'b010;
    4'b1010:
        O=3'b010;
    4'b1011:
        O=3'b100;
    4'b1100:
        O=3'b010;
    4'b1101:
        O=3'b100;
    4'b1110:
        O=3'b100;
    4'b1111:
        O=3'b100;
    default:
        O=3'b000;
endcase
endmodule

voter_tb.v
module voter_case_tb;
reg [3:0] In_tb;
wire [3:1] Out_tb;
voter voter_1(.I(In_tb), .O(Out_tb));
initial
begin
    #0  In_tb = 4'b0000;
    #10 In_tb = 4'b0001;
    #10 In_tb = 4'b0010;
    #10 In_tb = 4'b0011;
    #10 In_tb = 4'b0100;
    #10 In_tb = 4'b0101;
    #10 In_tb = 4'b0110;
    #10 In_tb = 4'b0111;
    #10 In_tb = 4'b1000;
    #10 In_tb = 4'b1001;
    #10 In_tb = 4'b1010;
    #10 In_tb = 4'b1011;
    #10 In_tb = 4'b1100;
    #10 In_tb = 4'b1101;
    #10 In_tb = 4'b1110;
    #10 In_tb = 4'b1111;
    #10 $finish;
end
initial
begin
    $dumpfile("voter.vcd");
    $dumpvars(0, voter_1);
end
endmodule

voter.vcd
$date
	Sat Apr 16 19:44:51 2022
$end
$version
	Icarus Verilog
$end
$timescale
	1s
$end
$scope module voter_case_tb $end
$scope module voter_1 $end
$var wire 4 ! I [3:0] $end
$var reg 3 " O [3:1] $end
$upscope $end
$upscope $end
$enddefinitions $end
#0
$dumpvars
b1 "
b0 !
$end
#10
b1 !
#20
b10 !
#30
b10 "
b11 !
#40
b1 "
b100 !
#50
b10 "
b101 !
#60
b110 !
#70
b100 "
b111 !
#80
b1 "
b1000 !
#90
b10 "
b1001 !
#100
b1010 !
#110
b100 "
b1011 !
#120
b10 "
b1100 !
#130
b100 "
b1101 !
#140
b1110 !
#150
b1111 !
